<?xml version="1.0" encoding="utf-8" ?>
<dwsync>
<file name="001.jpg" server="E:/AppServ/www/snwdw2/" local="130245542509853249" remote="130245542500000000" Dst="0" />
<file name="002.jpg" server="E:/AppServ/www/snwdw2/" local="130245542510083263" remote="130245542510000000" Dst="0" />
<file name="003.jpg" server="E:/AppServ/www/snwdw2/" local="130245542510193269" remote="130245542510000000" Dst="0" />
<file name="004.jpg" server="E:/AppServ/www/snwdw2/" local="130245542510603292" remote="130245542510000000" Dst="0" />
<file name="005.jpg" server="E:/AppServ/www/snwdw2/" local="130245542510873308" remote="130245542510000000" Dst="0" />
<file name="006.jpg" server="E:/AppServ/www/snwdw2/" local="130245542511503344" remote="130245542510000000" Dst="0" />
<file name="007.jpg" server="E:/AppServ/www/snwdw2/" local="130245542511353335" remote="130245542510000000" Dst="0" />
<file name="008.jpg" server="E:/AppServ/www/snwdw2/" local="130245542511513344" remote="130245542510000000" Dst="0" />
<file name="009.jpg" server="E:/AppServ/www/snwdw2/" local="130245542512283388" remote="130245542510000000" Dst="0" />
<file name="010.jpg" server="E:/AppServ/www/snwdw2/" local="130245542512373394" remote="130245542510000000" Dst="0" />
<file name="001.jpg" server="uhome.study365.org" local="130245542520000000" remote="130249717800000000" Dst="0" />
<file name="002.jpg" server="uhome.study365.org" local="130245542520000000" remote="130249717800000000" Dst="0" />
<file name="003.jpg" server="uhome.study365.org" local="130245542520000000" remote="130249717800000000" Dst="0" />
<file name="004.jpg" server="uhome.study365.org" local="130245542520000000" remote="130249717800000000" Dst="0" />
<file name="005.jpg" server="uhome.study365.org" local="130245542520000000" remote="130249717800000000" Dst="0" />
<file name="007.jpg" server="uhome.study365.org" local="130245542520000000" remote="130249717800000000" Dst="0" />
<file name="006.jpg" server="uhome.study365.org" local="130245542520000000" remote="130249717800000000" Dst="0" />
<file name="008.jpg" server="uhome.study365.org" local="130245542520000000" remote="130249717800000000" Dst="0" />
<file name="009.jpg" server="uhome.study365.org" local="130245542520000000" remote="130249717800000000" Dst="0" />
<file name="010.jpg" server="uhome.study365.org" local="130245542520000000" remote="130249717800000000" Dst="0" />
<file name="001.jpg" server="uhome2.study365.org//" local="130245542520000000" remote="130252794600000000" Dst="0" />
<file name="002.jpg" server="uhome2.study365.org//" local="130245542520000000" remote="130252794600000000" Dst="0" />
<file name="003.jpg" server="uhome2.study365.org//" local="130245542520000000" remote="130252794600000000" Dst="0" />
<file name="004.jpg" server="uhome2.study365.org//" local="130245542520000000" remote="130252794600000000" Dst="0" />
<file name="005.jpg" server="uhome2.study365.org//" local="130245542520000000" remote="130252794600000000" Dst="0" />
<file name="006.jpg" server="uhome2.study365.org//" local="130245542520000000" remote="130252794600000000" Dst="0" />
<file name="007.jpg" server="uhome2.study365.org//" local="130245542520000000" remote="130252794600000000" Dst="0" />
<file name="008.jpg" server="uhome2.study365.org//" local="130245542520000000" remote="130252794600000000" Dst="0" />
<file name="009.jpg" server="uhome2.study365.org//" local="130245542520000000" remote="130252794600000000" Dst="0" />
<file name="010.jpg" server="uhome2.study365.org//" local="130245542520000000" remote="130252794600000000" Dst="0" />
<file name="001.jpg" server="http://svn.paihangshuo.com/svn/uhome/" local="130260448350000000" remote="130260448350000000" Dst="0" />
<file name="010.jpg" server="http://svn.paihangshuo.com/svn/uhome/" local="130260448350000000" remote="130260448350000000" Dst="0" />
<file name="002.jpg" server="http://svn.paihangshuo.com/svn/uhome/" local="130260448350000000" remote="130260448350000000" Dst="0" />
<file name="003.jpg" server="http://svn.paihangshuo.com/svn/uhome/" local="130260448350000000" remote="130260448350000000" Dst="0" />
<file name="004.jpg" server="http://svn.paihangshuo.com/svn/uhome/" local="130260448350000000" remote="130260448350000000" Dst="0" />
<file name="005.jpg" server="http://svn.paihangshuo.com/svn/uhome/" local="130260448350000000" remote="130260448350000000" Dst="0" />
<file name="006.jpg" server="http://svn.paihangshuo.com/svn/uhome/" local="130260448350000000" remote="130260448350000000" Dst="0" />
<file name="007.jpg" server="http://svn.paihangshuo.com/svn/uhome/" local="130260448350000000" remote="130260448350000000" Dst="0" />
<file name="008.jpg" server="http://svn.paihangshuo.com/svn/uhome/" local="130260448350000000" remote="130260448350000000" Dst="0" />
<file name="009.jpg" server="http://svn.paihangshuo.com/svn/uhome/" local="130260448350000000" remote="130260448350000000" Dst="0" />
</dwsync>